venvinit/__init__.py
venvinit/venvinit.py
venvinit-0.0.5.dist-info/METADATA
venvinit-0.0.5.dist-info/WHEEL
venvinit-0.0.5.dist-info/entry_points.txt
venvinit-0.0.5.dist-info/licenses/LICENSE
venvinit-0.0.5.dist-info/RECORD
