Metadata-Version: 2.1
Name: venvinit
Version: 0.0.5
Summary: venvinit is a tool to create a virtual environment and install packages from a requirements file.
Project-URL: Bug Tracker, https://github.com/luxluth/venvinit/issues
Project-URL: Homepage, https://github.com/luxluth/venvinit
Author-email: Lux Luth <luxusluth@gmail.com>
License-File: LICENSE
Classifier: License :: OSI Approved :: MIT License
Classifier: Operating System :: OS Independent
Classifier: Programming Language :: Python :: 3
Requires-Python: >=3.6
Requires-Dist: certifi==2022.9.24
Requires-Dist: charset-normalizer==2.1.1
Requires-Dist: idna==3.4
Requires-Dist: requests==2.28.1
Requires-Dist: urllib3==1.26.12
